diffusion_core.cpython-312-darwin.so
diffusion_core-0.0.71.dist-info/LICENSE
diffusion_core-0.0.71.dist-info/METADATA
diffusion_core-0.0.71.dist-info/WHEEL
diffusion_core-0.0.71.dist-info/top_level.txt
diffusion_core-0.0.71.dist-info/RECORD
