Metadata-Version: 2.1
Name: diffusion-core
Version: 0.0.71
Summary: Python SDK for Diffusion - CBOR serialisation.
Author-email: DiffusionData Limited <contact@diffusiondata.com>
License: Proprietary
Project-URL: Homepage, https://www.diffusiondata.com/
Keywords: diffusion,cloud,websockets,data,delta
Classifier: License :: Other/Proprietary License
Classifier: Environment :: Other Environment
Classifier: Development Status :: 4 - Beta
Requires-Python: <3.13,>=3.8
License-File: LICENSE
